helloworld.py
helloworld_danlh-0.0.1.dist-info/LICENSE.txt
helloworld_danlh-0.0.1.dist-info/METADATA
helloworld_danlh-0.0.1.dist-info/WHEEL
helloworld_danlh-0.0.1.dist-info/top_level.txt
helloworld_danlh-0.0.1.dist-info/RECORD
